MANIFEST.in
setup.py
src/infi/__init__.py
src/infi.hbaapi.egg-info/PKG-INFO
src/infi.hbaapi.egg-info/SOURCES.txt
src/infi.hbaapi.egg-info/dependency_links.txt
src/infi.hbaapi.egg-info/entry_points.txt
src/infi.hbaapi.egg-info/namespace_packages.txt
src/infi.hbaapi.egg-info/not-zip-safe
src/infi.hbaapi.egg-info/requires.txt
src/infi.hbaapi.egg-info/top_level.txt
src/infi/hbaapi/__init__.py
src/infi/hbaapi/__version__.py
src/infi/hbaapi/examples/__init__.py
src/infi/hbaapi/examples/redhat6.py
src/infi/hbaapi/examples/windows.py
src/infi/hbaapi/generators/__init__.py
src/infi/hbaapi/generators/hbaapi/__init__.py
src/infi/hbaapi/generators/hbaapi/_hbaapi_aix.c
src/infi/hbaapi/generators/hbaapi/c_api.py
src/infi/hbaapi/generators/hbaapi/headers.py
src/infi/hbaapi/generators/sysfs/__init__.py
src/infi/hbaapi/generators/wmi/__init__.py
src/infi/hbaapi/scripts/__init__.py