Metadata-Version: 1.1
Name: infi.hbaapi
Version: 0.2.6
Summary: cross-platform bindings to FC-HBA APIs on Windows and Linux
Home-page: https://github.com/Infinidat/infi.hbaapi
Author: Guy Rozendorn
Author-email: guy@rzn.co.il
License: PSF
Platform: UNKNOWN
Classifier: Intended Audience :: Developers
Classifier: Intended Audience :: System Administrators
Classifier: License :: OSI Approved :: Python Software Foundation License
Classifier: Operating System :: OS Independent
Classifier: Programming Language :: Python
Classifier: Topic :: Software Development :: Libraries :: Python Modules
